<?xml version="1.1" encoding="UTF-8" standalone="no"?>
<databaseChangeLog xmlns="http://www.liquibase.org/xml/ns/dbchangelog" xmlns:ext="http://www.liquibase.org/xml/ns/dbchangelog-ext" xmlns:xsi="http://www.w3.org/2001/XMLSchema-instance" xsi:schemaLocation="http://www.liquibase.org/xml/ns/dbchangelog-ext http://www.liquibase.org/xml/ns/dbchangelog/dbchangelog-ext.xsd http://www.liquibase.org/xml/ns/dbchangelog http://www.liquibase.org/xml/ns/dbchangelog/dbchangelog-3.6.xsd">
    <changeSet author="liyunlong (generated)" id="1556963101018-1">
        <createTable remarks="应用表" tableName="t_app">
            <column autoIncrement="true" name="id" remarks="应用Id" type="BIGINT UNSIGNED">
                <constraints primaryKey="true"/>
            </column>
            <column name="app_id" type="VARCHAR(200)">
                <constraints nullable="false"/>
            </column>
            <column defaultValue="" name="name" remarks="应用名称" type="VARCHAR(200)">
                <constraints nullable="false"/>
            </column>
            <column defaultValue="" name="owner_name" remarks="负责人姓名" type="VARCHAR(200)">
                <constraints nullable="false"/>
            </column>
            <column defaultValue="0" name="owner_id" remarks="负责人Id" type="VARCHAR(200)"/>
            <column defaultValue="" name="project_name" remarks="所属项目名称" type="VARCHAR(200)">
                <constraints nullable="false"/>
            </column>
            <column defaultValue="0" name="project_key" remarks="所属项目Id" type="VARCHAR(200)">
                <constraints nullable="false"/>
            </column>
            <column defaultValue="" name="description" remarks="应用描述" type="VARCHAR(1000)"/>
            <column defaultValueDate="1970-01-02T00:00:00" name="gmt_create" remarks="创建时间" type="timestamp">
                <constraints nullable="false"/>
            </column>
            <column defaultValueComputed="CURRENT_TIMESTAMP" name="gmt_modified" remarks="更新时间" type="timestamp">
                <constraints nullable="false"/>
            </column>
            <column defaultValueNumeric="0" name="is_deleted" remarks="是否删除 0 否 1 已经删除" type="TINYINT(3)">
                <constraints nullable="false"/>
            </column>
            <column defaultValueNumeric="0" name="status" remarks="应用的状态 0-创建 1-开发中 2-运行中 3-已下线" type="TINYINT(3)"/>
            <column defaultValueNumeric="0" name="take_over" type="TINYINT(3)"/>
            <column name="ops_owner_name" type="VARCHAR(200)"/>
            <column name="ops_owner_id" type="VARCHAR(200)"/>
            <column name="repo_url" type="VARCHAR(1000)"/>
            <column name="bu_name" type="VARCHAR(255)"/>
            <column name="spring_application_name" type="VARCHAR(255)"/>
            <column defaultValueNumeric="0" name="spring_boot_version" type="INT"/>
            <column defaultValueNumeric="0" name="spring_cloud_version" type="INT"/>
        </createTable>
    </changeSet>
    <changeSet author="liyunlong (generated)" id="1556963101018-2">
        <createTable remarks="应用name表" tableName="t_app_name">
            <column autoIncrement="true" name="id" remarks="id" type="BIGINT UNSIGNED">
                <constraints primaryKey="true"/>
            </column>
            <column defaultValue="" name="name" remarks="应用名称" type="VARCHAR(200)">
                <constraints nullable="false"/>
            </column>
            <column defaultValueDate="1970-01-02T00:00:00" name="gmt_create" remarks="创建时间" type="timestamp">
                <constraints nullable="false"/>
            </column>
            <column defaultValueComputed="CURRENT_TIMESTAMP" name="gmt_modified" remarks="更新时间" type="timestamp">
                <constraints nullable="false"/>
            </column>
            <column defaultValueNumeric="0" name="is_deleted" remarks="是否删除 0 否 1 已经删除" type="TINYINT(3)">
                <constraints nullable="false"/>
            </column>
        </createTable>
    </changeSet>
    <changeSet author="liyunlong (generated)" id="1556963101018-3">
        <createTable remarks="数据字典详细表" tableName="t_dict_data">
            <column autoIncrement="true" name="id" remarks="数据字典详细主键" type="INT">
                <constraints primaryKey="true"/>
            </column>
            <column name="dict_code" remarks="数据字典分类标识" type="VARCHAR(64)">
                <constraints nullable="false"/>
            </column>
            <column name="item_name" remarks="数据字典详细名称" type="VARCHAR(64)">
                <constraints nullable="false"/>
            </column>
            <column name="item_value" remarks="数据字典详细值" type="VARCHAR(64)">
                <constraints nullable="false"/>
            </column>
            <column name="item_desc" remarks="数据字典详细描述" type="VARCHAR(64)"/>
            <column name="item_sort" remarks="排序" type="INT"/>
            <column defaultValueDate="1970-01-02T00:00:00" name="gmt_create" remarks="创建时间" type="timestamp">
                <constraints nullable="false"/>
            </column>
            <column defaultValueComputed="CURRENT_TIMESTAMP" name="gmt_modified" remarks="更新时间" type="timestamp">
                <constraints nullable="false"/>
            </column>
            <column defaultValueNumeric="0" name="is_deleted" remarks="是否删除 0 否 1 已经删除" type="TINYINT(3)">
                <constraints nullable="false"/>
            </column>
            <column defaultValueNumeric="0" name="status" remarks="COMMENT '数据字典项启用状态，1：启用，0：未启用'," type="TINYINT(3)"/>
        </createTable>
    </changeSet>
    <changeSet author="liyunlong (generated)" id="1556963101018-4">
        <createTable remarks="数据字典分类表" tableName="t_dict_type">
            <column autoIncrement="true" name="id" remarks="数据字典分类主键" type="INT">
                <constraints primaryKey="true"/>
            </column>
            <column name="dict_name" remarks="数据字典分类名称" type="VARCHAR(64)">
                <constraints nullable="false"/>
            </column>
            <column name="dict_code" remarks="数据字典分类唯一标识" type="VARCHAR(64)">
                <constraints nullable="false"/>
            </column>
            <column defaultValueNumeric="0" name="status" remarks="数据字典分类启用状态，0：启用，1：未启用" type="TINYINT(3)">
                <constraints nullable="false"/>
            </column>
            <column defaultValueDate="1970-01-02T00:00:00" name="gmt_create" remarks="创建时间" type="timestamp">
                <constraints nullable="false"/>
            </column>
            <column defaultValueComputed="CURRENT_TIMESTAMP" name="gmt_modified" remarks="更新时间" type="timestamp">
                <constraints nullable="false"/>
            </column>
            <column defaultValueNumeric="0" name="is_deleted" remarks="是否删除 0 否 1 已经删除" type="TINYINT(3)">
                <constraints nullable="false"/>
            </column>
        </createTable>
    </changeSet>
    <changeSet author="liyunlong (generated)" id="1556963101018-5">
        <createTable tableName="t_menu">
            <column autoIncrement="true" name="id" type="BIGINT">
                <constraints primaryKey="true"/>
            </column>
            <column name="parent_id" type="BIGINT"/>
            <column name="name" type="VARCHAR(255)"/>
            <column name="parent_ids" type="VARCHAR(255)"/>
            <column name="url" type="VARCHAR(255)"/>
            <column name="roles" type="VARCHAR(255)"/>
            <column defaultValueNumeric="1" name="sort" type="INT">
                <constraints nullable="false"/>
            </column>
            <column name="icon" type="VARCHAR(255)"/>
            <column defaultValueDate="1970-01-02T00:00:00" name="gmt_create" remarks="创建时间" type="timestamp">
                <constraints nullable="false"/>
            </column>
            <column defaultValueComputed="CURRENT_TIMESTAMP" name="gmt_modified" remarks="更新时间" type="timestamp">
                <constraints nullable="false"/>
            </column>
            <column defaultValueNumeric="0" name="is_deleted" remarks="是否删除 0 否 1 已经删除" type="TINYINT(3)">
                <constraints nullable="false"/>
            </column>
            <column name="key" type="VARCHAR(255)">
                <constraints nullable="false"/>
            </column>
        </createTable>
    </changeSet>
    <changeSet author="liyunlong (generated)" id="1556963101018-6">
        <createTable remarks="项目表" tableName="t_project">
            <column autoIncrement="true" name="id" remarks="项目Id" type="BIGINT UNSIGNED">
                <constraints primaryKey="true"/>
            </column>
            <column defaultValue="" name="name" remarks="项目名称" type="VARCHAR(200)">
                <constraints nullable="false"/>
            </column>
            <column defaultValue="" name="cname" remarks="项目中文名称" type="VARCHAR(200)">
                <constraints nullable="false"/>
            </column>
            <column defaultValue="0" name="key" remarks="项目key" type="VARCHAR(200)">
                <constraints nullable="false"/>
            </column>
            <column defaultValue="" name="owner_name" remarks="负责人姓名" type="VARCHAR(200)">
                <constraints nullable="false"/>
            </column>
            <column defaultValue="0" name="owner_id" remarks="负责人Id" type="VARCHAR(200)"/>
            <column defaultValue="" name="description" remarks="项目描述" type="VARCHAR(1000)"/>
            <column defaultValueDate="1970-01-02T00:00:00" name="gmt_create" remarks="创建时间" type="timestamp">
                <constraints nullable="false"/>
            </column>
            <column defaultValueComputed="CURRENT_TIMESTAMP" name="gmt_modified" remarks="更新时间" type="timestamp">
                <constraints nullable="false"/>
            </column>
            <column defaultValueNumeric="0" name="is_deleted" remarks="是否删除 0 否 1 已经删除" type="TINYINT(3)">
                <constraints nullable="false"/>
            </column>
        </createTable>
    </changeSet>
    <changeSet author="liyunlong (generated)" id="1556963101018-7">
        <createTable remarks="注册中心表" tableName="t_register_center">
            <column autoIncrement="true" name="id" type="INT">
                <constraints primaryKey="true"/>
            </column>
            <column name="code" remarks="注册中心标识" type="VARCHAR(50)">
                <constraints nullable="false"/>
            </column>
            <column name="url" remarks="注册中心url" type="VARCHAR(100)">
                <constraints nullable="false"/>
            </column>
            <column name="desc" remarks="描述" type="VARCHAR(64)"/>
            <column name="status" remarks="1 运行,0 停用" type="BIT(1)">
                <constraints nullable="false"/>
            </column>
            <column defaultValueDate="1970-01-02T00:00:00" name="gmt_create" remarks="创建时间" type="timestamp">
                <constraints nullable="false"/>
            </column>
            <column defaultValueComputed="CURRENT_TIMESTAMP" name="gmt_modified" remarks="更新时间" type="timestamp">
                <constraints nullable="false"/>
            </column>
            <column defaultValueNumeric="0" name="is_deleted" remarks="是否删除 0 否 1 已经删除" type="TINYINT(3)">
                <constraints nullable="false"/>
            </column>
            <column name="name" type="VARCHAR(50)"/>
        </createTable>
    </changeSet>
    <changeSet author="liyunlong (generated)" id="1556963101018-8">
        <createTable remarks="用户表" tableName="t_user">
            <column autoIncrement="true" name="id" type="INT">
                <constraints primaryKey="true"/>
            </column>
            <column name="username" remarks="英文名唯一" type="VARCHAR(50)">
                <constraints nullable="false"/>
            </column>
            <column name="name" remarks="中文名" type="VARCHAR(50)">
                <constraints nullable="false"/>
            </column>
            <column name="password" remarks="密码" type="VARCHAR(50)">
                <constraints nullable="false"/>
            </column>
            <column name="status" remarks="是否启用" type="BIT(1)">
                <constraints nullable="false"/>
            </column>
            <column defaultValueDate="1970-01-02T00:00:00" name="gmt_create" remarks="创建时间" type="timestamp">
                <constraints nullable="false"/>
            </column>
            <column defaultValueComputed="CURRENT_TIMESTAMP" name="gmt_modified" remarks="更新时间" type="timestamp">
                <constraints nullable="false"/>
            </column>
            <column defaultValueNumeric="0" name="is_deleted" remarks="是否删除 0 否 1 已经删除" type="TINYINT(3)">
                <constraints nullable="false"/>
            </column>
            <column name="email" type="VARCHAR(255)"/>
        </createTable>
    </changeSet>
    <changeSet author="liyunlong (generated)" id="1556963101018-9">
        <createTable remarks="应用name表" tableName="t_user_app">
            <column autoIncrement="true" name="id" remarks="id" type="BIGINT UNSIGNED">
                <constraints primaryKey="true"/>
            </column>
            <column defaultValue="" name="mail_nick_name" remarks="邮箱前缀名称" type="VARCHAR(200)">
                <constraints nullable="false"/>
            </column>
            <column defaultValue="" name="app_id" remarks="应用名称" type="VARCHAR(200)">
                <constraints nullable="false"/>
            </column>
            <column defaultValueDate="1970-01-02T00:00:00" name="gmt_create" remarks="创建时间" type="timestamp">
                <constraints nullable="false"/>
            </column>
            <column defaultValueComputed="CURRENT_TIMESTAMP" name="gmt_modified" remarks="更新时间" type="timestamp">
                <constraints nullable="false"/>
            </column>
            <column defaultValueNumeric="0" name="is_deleted" remarks="是否删除 0 否 1 已经删除" type="TINYINT(3)">
                <constraints nullable="false"/>
            </column>
        </createTable>
    </changeSet>
    <changeSet author="liyunlong (generated)" id="1556963101018-10">
        <createTable tableName="t_user_roles">
            <column autoIncrement="true" name="id" type="INT">
                <constraints primaryKey="true"/>
            </column>
            <column name="username" type="VARCHAR(50)">
                <constraints nullable="false"/>
            </column>
            <column name="role" type="VARCHAR(50)">
                <constraints nullable="false"/>
            </column>
            <column defaultValueDate="1970-01-02T00:00:00" name="gmt_create" remarks="创建时间" type="timestamp">
                <constraints nullable="false"/>
            </column>
            <column defaultValueComputed="CURRENT_TIMESTAMP" name="gmt_modified" remarks="更新时间" type="timestamp">
                <constraints nullable="false"/>
            </column>
            <column defaultValueNumeric="0" name="is_deleted" remarks="是否删除 0 否 1 已经删除" type="TINYINT(3)">
                <constraints nullable="false"/>
            </column>
        </createTable>
    </changeSet>
    <changeSet author="liyunlong (generated)" id="1556963101018-11">
        <insert tableName="t_app">
            <column name="id" valueNumeric="1"/>
            <column name="app_id" value="halo-moss"/>
            <column name="name" value="halo-moss"/>
            <column name="owner_name" value="许进"/>
            <column name="owner_id" value="xujin"/>
            <column name="project_name" value="halo"/>
            <column name="project_key" value="Halo"/>
            <column name="description" value=""/>
            <column name="gmt_create" valueDate="2019-02-27T16:23:42"/>
            <column name="gmt_modified" valueDate="2019-04-21T23:15:04"/>
            <column name="is_deleted" valueNumeric="0"/>
            <column name="status" valueNumeric="2"/>
            <column name="take_over" valueNumeric="1"/>
            <column name="ops_owner_name" value="韩令三"/>
            <column name="ops_owner_id" value="lingshan.han"/>
            <column name="repo_url" value="https://github.com/SoftwareKing/Moss.git"/>
            <column name="bu_name" value="XX"/>
            <column name="spring_application_name" value="halo-moss"/>
            <column name="spring_boot_version" valueNumeric="2"/>
            <column name="spring_cloud_version" valueNumeric="2"/>
        </insert>
        <insert tableName="t_app">
            <column name="id" valueNumeric="2"/>
            <column name="app_id" value="moss-sample-1.5.x"/>
            <column name="name" value="moss-sample-1.5.x"/>
            <column name="owner_name" value="杜为极"/>
            <column name="owner_id" value="weiji.du"/>
            <column name="project_name" value="BKCASHIER"/>
            <column name="project_key" value="MOSS"/>
            <column name="description" value=""/>
            <column name="gmt_create" valueDate="2019-02-27T16:23:42"/>
            <column name="gmt_modified" valueDate="2019-04-21T23:15:27"/>
            <column name="is_deleted" valueNumeric="0"/>
            <column name="status" valueNumeric="2"/>
            <column name="take_over" valueNumeric="1"/>
            <column name="ops_owner_name" value="叶张"/>
            <column name="ops_owner_id" value="dingf.ye001"/>
            <column name="repo_url" value="https://github.com/SoftwareKing/Moss.git"/>
            <column name="bu_name" value="金融XX"/>
            <column name="spring_application_name" value="moss-sample-1.5.x"/>
            <column name="spring_boot_version" valueNumeric="1"/>
            <column name="spring_cloud_version" valueNumeric="1"/>
        </insert>
        <insert tableName="t_app">
            <column name="id" valueNumeric="3"/>
            <column name="app_id" value="hdata-labhub"/>
            <column name="name" value="moss-sample-2.1.x"/>
            <column name="owner_name" value="许进"/>
            <column name="owner_id" value="guojian.li"/>
            <column name="project_name" value="MOSS"/>
            <column name="project_key" value="MOSS"/>
            <column name="description" value=""/>
            <column name="gmt_create" valueDate="2019-02-27T16:23:42"/>
            <column name="gmt_modified" valueDate="2019-04-21T23:15:22"/>
            <column name="is_deleted" valueNumeric="0"/>
            <column name="status" valueNumeric="2"/>
            <column name="take_over" valueNumeric="1"/>
            <column name="ops_owner_name" value="齐思宇"/>
            <column name="ops_owner_id" value="daiying.qi"/>
            <column name="repo_url" value="https://github.com/SoftwareKing/Moss.git"/>
            <column name="bu_name" value="房XX"/>
            <column name="spring_application_name" value="moss-sample-2.1.x"/>
            <column name="spring_boot_version" valueNumeric="2"/>
            <column name="spring_cloud_version" valueNumeric="2"/>
        </insert>
    </changeSet>
    <changeSet author="liyunlong (generated)" id="1556963101018-12">
        <insert tableName="t_dict_data">
            <column name="id" valueNumeric="1"/>
            <column name="dict_code" value="springBootVersion"/>
            <column name="item_name" value="1.5.13.RELEASE"/>
            <column name="item_value" value="1"/>
            <column name="item_desc" value="1.5.13.RELEASE"/>
            <column name="item_sort" valueNumeric="0"/>
            <column name="gmt_create" valueDate="1970-01-02T14:00:00"/>
            <column name="gmt_modified" valueDate="2019-03-16T06:44:15"/>
            <column name="is_deleted" valueNumeric="0"/>
            <column name="status" valueNumeric="1"/>
        </insert>
        <insert tableName="t_dict_data">
            <column name="id" valueNumeric="2"/>
            <column name="dict_code" value="springBootVersion"/>
            <column name="item_name" value="2.0.7.RELEASE"/>
            <column name="item_value" value="2"/>
            <column name="item_desc" value="2.0.7.RELEASE"/>
            <column name="item_sort" valueNumeric="0"/>
            <column name="gmt_create" valueDate="1970-01-02T14:00:00"/>
            <column name="gmt_modified" valueDate="2019-03-16T06:44:19"/>
            <column name="is_deleted" valueNumeric="0"/>
            <column name="status" valueNumeric="1"/>
        </insert>
        <insert tableName="t_dict_data">
            <column name="id" valueNumeric="3"/>
            <column name="dict_code" value="springCloudVersion"/>
            <column name="item_name" value="Edgware.SR3"/>
            <column name="item_value" value="1"/>
            <column name="item_desc" value="Spring Cloud Edgware.SR3"/>
            <column name="item_sort" valueNumeric="0"/>
            <column name="gmt_create" valueDate="1970-01-02T14:00:00"/>
            <column name="gmt_modified" valueDate="2019-03-16T06:44:27"/>
            <column name="is_deleted" valueNumeric="0"/>
            <column name="status" valueNumeric="1"/>
        </insert>
        <insert tableName="t_dict_data">
            <column name="id" valueNumeric="4"/>
            <column name="dict_code" value="springCloudVersion"/>
            <column name="item_name" value="Finchley.SR2"/>
            <column name="item_value" value="2"/>
            <column name="item_desc" value="Spring Cloud Finchley.SR2"/>
            <column name="item_sort" valueNumeric="0"/>
            <column name="gmt_create" valueDate="1970-01-02T14:00:00"/>
            <column name="gmt_modified" valueDate="2019-03-16T06:44:31"/>
            <column name="is_deleted" valueNumeric="0"/>
            <column name="status" valueNumeric="1"/>
        </insert>
        <insert tableName="t_dict_data">
            <column name="id" valueNumeric="5"/>
            <column name="dict_code" value="frameworkVerison"/>
            <column name="item_name" value="1.1.8.RELEASE"/>
            <column name="item_value" value="1"/>
            <column name="item_desc" value="1.1.8.RELEASE"/>
            <column name="item_sort" valueNumeric="0"/>
            <column name="gmt_create" valueDate="1970-01-02T14:00:00"/>
            <column name="gmt_modified" valueDate="2019-04-11T08:58:48"/>
            <column name="is_deleted" valueNumeric="1"/>
            <column name="status" valueNumeric="1"/>
        </insert>
        <insert tableName="t_dict_data">
            <column name="id" valueNumeric="6"/>
            <column name="dict_code" value="frameworkVerison"/>
            <column name="item_name" value="2.0.0.RELEASE"/>
            <column name="item_value" value="2"/>
            <column name="item_desc" value="2.0.0.RELEASE"/>
            <column name="item_sort" valueNumeric="0"/>
            <column name="gmt_create" valueDate="1970-01-02T14:00:00"/>
            <column name="gmt_modified" valueDate="2019-04-11T08:58:48"/>
            <column name="is_deleted" valueNumeric="1"/>
            <column name="status" valueNumeric="1"/>
        </insert>
        <insert tableName="t_dict_data">
            <column name="id" valueNumeric="11"/>
            <column name="dict_code" value="appFlickerRule"/>
            <column name="item_name" value="当实例数小于2"/>
            <column name="item_value" value="1"/>
            <column name="item_desc" value="当实例数小于2时闪烁"/>
            <column name="item_sort" valueNumeric="0"/>
            <column name="gmt_create" valueDate="1970-01-02T14:00:00"/>
            <column name="gmt_modified" valueDate="2019-03-20T02:44:36"/>
            <column name="is_deleted" valueNumeric="0"/>
            <column name="status" valueNumeric="1"/>
        </insert>
        <insert tableName="t_dict_data">
            <column name="id" valueNumeric="12"/>
            <column name="dict_code" value="scoringRules"/>
            <column name="item_name" value="当实例数大于1"/>
            <column name="item_value" value="1"/>
            <column name="item_desc" value="当实例数大于1给1颗星"/>
            <column name="item_sort" valueNumeric="0"/>
            <column name="gmt_create" valueDate="1970-01-02T14:00:00"/>
            <column name="gmt_modified" valueDate="2019-03-20T02:42:48"/>
            <column name="is_deleted" valueNumeric="0"/>
            <column name="status" valueNumeric="1"/>
        </insert>
    </changeSet>
    <changeSet author="liyunlong (generated)" id="1556963101018-13">
        <insert tableName="t_dict_type">
            <column name="id" valueNumeric="1"/>
            <column name="dict_name" value="Spring Boot的版本"/>
            <column name="dict_code" value="springBootVersion"/>
            <column name="status" valueNumeric="0"/>
            <column name="gmt_create" valueDate="2019-03-12T15:36:02"/>
            <column name="gmt_modified" valueDate="2019-03-15T03:17:10"/>
            <column name="is_deleted" valueNumeric="0"/>
        </insert>
        <insert tableName="t_dict_type">
            <column name="id" valueNumeric="2"/>
            <column name="dict_name" value="Spring Cloud的版本"/>
            <column name="dict_code" value="springCloudVersion"/>
            <column name="status" valueNumeric="0"/>
            <column name="gmt_create" valueDate="2019-03-12T15:36:42"/>
            <column name="gmt_modified" valueDate="2019-03-15T03:17:27"/>
            <column name="is_deleted" valueNumeric="0"/>
        </insert>
        <insert tableName="t_dict_type">
            <column name="id" valueNumeric="3"/>
            <column name="dict_name" value="Summer Framework的版本"/>
            <column name="dict_code" value="frameworkVerison"/>
            <column name="status" valueNumeric="0"/>
            <column name="gmt_create" valueDate="2019-03-12T15:37:21"/>
            <column name="gmt_modified" valueDate="2019-03-15T03:17:41"/>
            <column name="is_deleted" valueNumeric="1"/>
        </insert>
        <insert tableName="t_dict_type">
            <column name="id" valueNumeric="6"/>
            <column name="dict_name" value="App根据实例数闪烁规则"/>
            <column name="dict_code" value="appFlickerRule"/>
            <column name="status" valueNumeric="0"/>
            <column name="gmt_create" valueDate="2019-03-15T14:55:56"/>
            <column name="gmt_modified" valueDate="2019-03-15T14:55:56"/>
            <column name="is_deleted" valueNumeric="0"/>
        </insert>
        <insert tableName="t_dict_type">
            <column name="id" valueNumeric="7"/>
            <column name="dict_name" value="评分规则"/>
            <column name="dict_code" value="scoringRules"/>
            <column name="status" valueNumeric="0"/>
            <column name="gmt_create" valueDate="2019-03-15T14:56:22"/>
            <column name="gmt_modified" valueDate="2019-03-15T14:56:22"/>
            <column name="is_deleted" valueNumeric="0"/>
        </insert>
    </changeSet>
    <changeSet author="liyunlong (generated)" id="1556963101018-14">
        <insert tableName="t_menu">
            <column name="id" valueNumeric="1"/>
            <column name="parent_id" valueNumeric="0"/>
            <column name="name" value="总览"/>
            <column name="parent_ids" value="0"/>
            <column name="url" value="/dashboard"/>
            <column name="roles" value="USER,ADMIN"/>
            <column name="sort" valueNumeric="6"/>
            <column name="icon" value="dashboard"/>
            <column name="gmt_create" valueDate="1970-01-02T14:00:00"/>
            <column name="gmt_modified" valueDate="2019-03-02T08:36:14"/>
            <column name="is_deleted" valueNumeric="0"/>
            <column name="key" value="dashboard"/>
        </insert>
        <insert tableName="t_menu">
            <column name="id" valueNumeric="2"/>
            <column name="parent_id" valueNumeric="0"/>
            <column name="name" value="服务治理"/>
            <column name="parent_ids" value="0"/>
            <column name="url" value="/#/application"/>
            <column name="roles" value="USER,ADMIN"/>
            <column name="sort" valueNumeric="5"/>
            <column name="icon" value="appstore"/>
            <column name="gmt_create" valueDate="1970-01-02T14:00:00"/>
            <column name="gmt_modified" valueDate="2019-03-02T07:34:03"/>
            <column name="is_deleted" valueNumeric="0"/>
            <column name="key" value="serviceMgmt"/>
        </insert>
        <insert tableName="t_menu">
            <column name="id" valueNumeric="5"/>
            <column name="parent_id" valueNumeric="0"/>
            <column name="name" value="平台管理"/>
            <column name="parent_ids" value="0"/>
            <column name="url" value="/#"/>
            <column name="roles" value="USER,ADMIN"/>
            <column name="sort" valueNumeric="1"/>
            <column name="icon" value="hdd"/>
            <column name="gmt_create" valueDate="1970-01-02T14:00:00"/>
            <column name="gmt_modified" valueDate="2019-04-04T17:12:52"/>
            <column name="is_deleted" valueNumeric="0"/>
            <column name="key" value="projectMgmt"/>
        </insert>
        <insert tableName="t_menu">
            <column name="id" valueNumeric="6"/>
            <column name="parent_id" valueNumeric="4"/>
            <column name="name" value="推送记录"/>
            <column name="parent_ids" value="0"/>
            <column name="url" value="/switchCenter"/>
            <column name="roles" value="USER,ADMIN"/>
            <column name="sort" valueNumeric="1"/>
            <column name="icon" value="code"/>
            <column name="gmt_create" valueDate="1970-01-02T14:00:00"/>
            <column name="gmt_modified" valueDate="2019-01-04T06:21:07"/>
            <column name="is_deleted" valueNumeric="0"/>
            <column name="key" value="switchPushLog"/>
        </insert>
        <insert tableName="t_menu">
            <column name="id" valueNumeric="10"/>
            <column name="parent_id" valueNumeric="4"/>
            <column name="name" value="开关管理"/>
            <column name="parent_ids" value="0"/>
            <column name="url" value="/switchCenter"/>
            <column name="roles" value="USER,ADMIN"/>
            <column name="sort" valueNumeric="1"/>
            <column name="icon" value="key"/>
            <column name="gmt_create" valueDate="1970-01-02T14:00:00"/>
            <column name="gmt_modified" valueDate="2019-01-04T01:01:32"/>
            <column name="is_deleted" valueNumeric="0"/>
            <column name="key" value="switchManage"/>
        </insert>
        <insert tableName="t_menu">
            <column name="id" valueNumeric="11"/>
            <column name="parent_id" valueNumeric="4"/>
            <column name="name" value="机器管理"/>
            <column name="parent_ids" value="0"/>
            <column name="url"/>
            <column name="roles" value="USER,ADMIN"/>
            <column name="sort" valueNumeric="1"/>
            <column name="icon" value="database"/>
            <column name="gmt_create" valueDate="1970-01-02T14:00:00"/>
            <column name="gmt_modified" valueDate="2018-12-11T04:04:18"/>
            <column name="is_deleted" valueNumeric="0"/>
            <column name="key" value="machine"/>
        </insert>
        <insert tableName="t_menu">
            <column name="id" valueNumeric="12"/>
            <column name="parent_id" valueNumeric="0"/>
            <column name="name" value="系统管理"/>
            <column name="parent_ids" value="0"/>
            <column name="url" value=""/>
            <column name="roles" value="ADMIN"/>
            <column name="sort" valueNumeric="1"/>
            <column name="icon" value="setting"/>
            <column name="gmt_create" valueDate="1970-01-02T14:00:00"/>
            <column name="gmt_modified" valueDate="2018-12-11T04:15:55"/>
            <column name="is_deleted" valueNumeric="0"/>
            <column name="key" value="sys"/>
        </insert>
        <insert tableName="t_menu">
            <column name="id" valueNumeric="13"/>
            <column name="parent_id" valueNumeric="12"/>
            <column name="name" value="菜单管理"/>
            <column name="parent_ids" value="0"/>
            <column name="url" value="/OSManage"/>
            <column name="roles" value="USER,ADMIN"/>
            <column name="sort" valueNumeric="1"/>
            <column name="icon" value="profile"/>
            <column name="gmt_create" valueDate="1970-01-02T14:00:00"/>
            <column name="gmt_modified" valueDate="2018-12-11T04:04:24"/>
            <column name="is_deleted" valueNumeric="0"/>
            <column name="key" value="menuManage"/>
        </insert>
        <insert tableName="t_menu">
            <column name="id" valueNumeric="16"/>
            <column name="parent_id" valueNumeric="5"/>
            <column name="name" value="应用管理"/>
            <column name="parent_ids" value="0"/>
            <column name="url" value="/application"/>
            <column name="roles" value="ADMIN"/>
            <column name="sort" valueNumeric="1"/>
            <column name="icon" value="euro"/>
            <column name="gmt_create" valueDate="1970-01-02T14:00:00"/>
            <column name="gmt_modified" valueDate="2019-04-20T10:47:35"/>
            <column name="is_deleted" valueNumeric="0"/>
            <column name="key" value="appAccept"/>
        </insert>
        <insert tableName="t_menu">
            <column name="id" valueNumeric="24"/>
            <column name="parent_id" valueNumeric="2"/>
            <column name="name" value="服务管理"/>
            <column name="parent_ids" value="0"/>
            <column name="url" value="/application"/>
            <column name="roles" value="USER,ADMIN"/>
            <column name="sort" valueNumeric="5"/>
            <column name="icon" value="deployment-unit"/>
            <column name="gmt_create" valueDate="2019-02-22T17:21:10"/>
            <column name="gmt_modified" valueDate="2019-04-20T10:49:06"/>
            <column name="is_deleted" valueNumeric="0"/>
            <column name="key" value="serviceManage"/>
        </insert>
        <insert tableName="t_menu">
            <column name="id" valueNumeric="25"/>
            <column name="parent_id" valueNumeric="2"/>
            <column name="name" value="事件中心"/>
            <column name="parent_ids" value="0"/>
            <column name="url" value="/application"/>
            <column name="roles" value="USER,ADMIN"/>
            <column name="sort" valueNumeric="0"/>
            <column name="icon" value="setting"/>
            <column name="gmt_create" valueDate="2019-02-25T17:22:10"/>
            <column name="gmt_modified" valueDate="2019-02-25T17:22:24"/>
            <column name="is_deleted" valueNumeric="0"/>
            <column name="key" value="eventLog"/>
        </insert>
        <insert tableName="t_menu">
            <column name="id" valueNumeric="26"/>
            <column name="parent_id" valueNumeric="2"/>
            <column name="name" value="实例管理"/>
            <column name="parent_ids" value="0"/>
            <column name="url" value="/application"/>
            <column name="roles" value="USER,ADMIN"/>
            <column name="sort" valueNumeric="3"/>
            <column name="icon" value="ant-design"/>
            <column name="gmt_create" valueDate="1970-01-02T14:00:00"/>
            <column name="gmt_modified" valueDate="2019-04-20T10:50:22"/>
            <column name="is_deleted" valueNumeric="0"/>
            <column name="key" value="list"/>
        </insert>
        <insert tableName="t_menu">
            <column name="id" valueNumeric="27"/>
            <column name="parent_id" valueNumeric="5"/>
            <column name="name" value="项目列表"/>
            <column name="parent_ids" value="0"/>
            <column name="url" value="/application"/>
            <column name="roles" value="ADMIN"/>
            <column name="sort" valueNumeric="2"/>
            <column name="icon" value="project"/>
            <column name="gmt_create" valueDate="2019-03-07T16:33:31"/>
            <column name="gmt_modified" valueDate="2019-04-20T10:48:32"/>
            <column name="is_deleted" valueNumeric="0"/>
            <column name="key" value="Project"/>
        </insert>
        <insert tableName="t_menu">
            <column name="id" valueNumeric="28"/>
            <column name="parent_id" valueNumeric="12"/>
            <column name="name" value="用户列表"/>
            <column name="parent_ids" value="0"/>
            <column name="url" value="/userMgmt"/>
            <column name="roles" value="USER,ADMIN"/>
            <column name="sort" valueNumeric="0"/>
            <column name="icon" value="user"/>
            <column name="gmt_create" valueDate="2019-03-07T16:35:53"/>
            <column name="gmt_modified" valueDate="2019-04-04T19:53:52"/>
            <column name="is_deleted" valueNumeric="0"/>
            <column name="key" value="userMgmt"/>
        </insert>
        <insert tableName="t_menu">
            <column name="id" valueNumeric="30"/>
            <column name="parent_id" valueNumeric="12"/>
            <column name="name" value="数据字典"/>
            <column name="parent_ids" value="0"/>
            <column name="url" value="/remoteConfig"/>
            <column name="roles" value="ADMIN"/>
            <column name="sort" valueNumeric="0"/>
            <column name="icon" value="appstore"/>
            <column name="gmt_create" valueDate="2019-03-13T16:10:28"/>
            <column name="gmt_modified" valueDate="2019-03-13T16:10:28"/>
            <column name="is_deleted" valueNumeric="0"/>
            <column name="key" value="remoteConfig"/>
        </insert>
        <insert tableName="t_menu">
            <column name="id" valueNumeric="31"/>
            <column name="parent_id" valueNumeric="5"/>
            <column name="name" value="注册中心"/>
            <column name="parent_ids" value="0"/>
            <column name="url" value="/registerCenterMgmt"/>
            <column name="roles" value="ADMIN"/>
            <column name="sort" valueNumeric="0"/>
            <column name="icon" value="gateway"/>
            <column name="gmt_create" valueDate="2019-04-04T17:13:20"/>
            <column name="gmt_modified" valueDate="2019-04-20T10:48:02"/>
            <column name="is_deleted" valueNumeric="0"/>
            <column name="key" value="registerCenterMgmt"/>
        </insert>
    </changeSet>
    <changeSet author="liyunlong (generated)" id="1556963101018-15">
        <insert tableName="t_project">
            <column name="id" valueNumeric="1"/>
            <column name="name" value="服务治理"/>
            <column name="cname" value="服务治理"/>
            <column name="key" value="MOSS"/>
            <column name="owner_name" value="许进"/>
            <column name="owner_id" value="xujin"/>
            <column name="description" value="服务治理"/>
            <column name="gmt_create" valueDate="2019-03-01T11:01:18"/>
            <column name="gmt_modified" valueDate="2019-04-06T03:42:36"/>
            <column name="is_deleted" valueNumeric="0"/>
        </insert>
        <insert tableName="t_project">
            <column name="id" valueNumeric="2"/>
            <column name="name" value="中台项目"/>
            <column name="cname" value="中台项目"/>
            <column name="key" value="HALO"/>
            <column name="owner_name" value="许进"/>
            <column name="owner_id" value="xujin"/>
            <column name="description" value=""/>
            <column name="gmt_create" valueDate="2019-03-01T11:02:25"/>
            <column name="gmt_modified" valueDate="2019-04-06T03:43:09"/>
            <column name="is_deleted" valueNumeric="0"/>
        </insert>
        <insert tableName="t_project">
            <column name="id" valueNumeric="3"/>
            <column name="name" value="PMO"/>
            <column name="cname" value="PMO"/>
            <column name="key" value="PMO"/>
            <column name="owner_name" value="黎茂"/>
            <column name="owner_id" value="mao.li001"/>
            <column name="description" value=""/>
            <column name="gmt_create" valueDate="2019-03-01T11:02:25"/>
            <column name="gmt_modified" valueDate="2019-03-08T06:45:13"/>
            <column name="is_deleted" valueNumeric="1"/>
        </insert>
        <insert tableName="t_project">
            <column name="id" valueNumeric="4"/>
            <column name="name" value="XXXUED"/>
            <column name="cname" value="XXXUED"/>
            <column name="key" value="UED"/>
            <column name="owner_name" value="王佳琳"/>
            <column name="owner_id" value="jialin.wang"/>
            <column name="description" value=""/>
            <column name="gmt_create" valueDate="2019-03-01T11:02:26"/>
            <column name="gmt_modified" valueDate="2019-03-08T06:45:17"/>
            <column name="is_deleted" valueNumeric="1"/>
        </insert>
    </changeSet>
    <changeSet author="liyunlong (generated)" id="1556963101018-16">
        <insert tableName="t_register_center">
            <column name="id" valueNumeric="1"/>
            <column name="code" value="sq"/>
            <column name="url" value="http://eureka.springcloud.cn/eureka/"/>
            <column name="desc" value="社区注册"/>
            <column name="status" valueBoolean="true"/>
            <column name="gmt_create" valueDate="2019-04-04T17:28:11"/>
            <column name="gmt_modified" valueDate="2019-04-06T07:54:45"/>
            <column name="is_deleted" valueNumeric="0"/>
            <column name="name" value="社区注册"/>
        </insert>
        <insert tableName="t_register_center">
            <column name="id" valueNumeric="4"/>
            <column name="code" value="zj"/>
            <column name="url" value="http://localhost:8071/eureka"/>
            <column name="desc" value="自己本地"/>
            <column name="status" valueBoolean="false"/>
            <column name="gmt_create" valueDate="2019-04-21T11:37:04"/>
            <column name="gmt_modified" valueDate="2019-04-22T00:37:25"/>
            <column name="is_deleted" valueNumeric="0"/>
            <column name="name" value="自己本地"/>
        </insert>
        <insert tableName="t_register_center">
            <column name="id" valueNumeric="5"/>
            <column name="code" value="work"/>
            <column name="url" value="http://admin:123456@172.16.138.138:8761/eureka"/>
            <column name="desc" value="ttt"/>
            <column name="status" valueBoolean="true"/>
            <column name="gmt_create" valueDate="2019-05-04T17:17:57"/>
            <column name="gmt_modified" valueDate="2019-05-04T17:17:57"/>
            <column name="is_deleted" valueNumeric="0"/>
            <column name="name" value="work"/>
        </insert>
    </changeSet>
    <changeSet author="liyunlong (generated)" id="1556963101018-17">
        <insert tableName="t_user">
            <column name="id" valueNumeric="1"/>
            <column name="username" value="xujin"/>
            <column name="name" value="xujin"/>
            <column name="password" value="UUKHSDDI5KPA43A8VL06V0TU2"/>
            <column name="status" valueBoolean="false"/>
            <column name="gmt_create" valueDate="2019-03-07T10:23:50"/>
            <column name="gmt_modified" valueDate="2019-03-09T09:15:35"/>
            <column name="is_deleted" valueNumeric="0"/>
            <column name="email" value="Software_King@qq.com"/>
        </insert>
        <insert tableName="t_user">
            <column name="id" valueNumeric="6"/>
            <column name="username" value="admin"/>
            <column name="name" value="admin"/>
            <column name="password" value="UUKHSDDI5KPA43A8VL06V0TU2"/>
            <column name="status" valueBoolean="false"/>
            <column name="gmt_create" valueDate="2019-04-12T17:37:00"/>
            <column name="gmt_modified" valueDate="2019-04-22T00:38:48"/>
            <column name="is_deleted" valueNumeric="0"/>
            <column name="email" value="admin@qq.com"/>
        </insert>
    </changeSet>
    <changeSet author="liyunlong (generated)" id="1556963101018-18">
        <insert tableName="t_user_app">
            <column name="id" valueNumeric="38"/>
            <column name="mail_nick_name" value="xujin"/>
            <column name="app_id" value="halo-moss"/>
            <column name="gmt_create" valueDate="2019-03-10T18:46:39"/>
            <column name="gmt_modified" valueDate="2019-04-05T14:31:23"/>
            <column name="is_deleted" valueNumeric="1"/>
        </insert>
        <insert tableName="t_user_app">
            <column name="id" valueNumeric="39"/>
            <column name="mail_nick_name" value="xujin"/>
            <column name="app_id" value="loop_test"/>
            <column name="gmt_create" valueDate="2019-03-10T20:44:23"/>
            <column name="gmt_modified" valueDate="2019-03-10T20:44:27"/>
            <column name="is_deleted" valueNumeric="1"/>
        </insert>
        <insert tableName="t_user_app">
            <column name="id" valueNumeric="40"/>
            <column name="mail_nick_name" value="admin"/>
            <column name="app_id" value="halo-moss"/>
            <column name="gmt_create" valueDate="2019-03-12T11:45:05"/>
            <column name="gmt_modified" valueDate="2019-03-12T11:45:07"/>
            <column name="is_deleted" valueNumeric="1"/>
        </insert>
        <insert tableName="t_user_app">
            <column name="id" valueNumeric="41"/>
            <column name="mail_nick_name" value="test"/>
            <column name="app_id" value="halo-moss"/>
            <column name="gmt_create" valueDate="2019-03-12T13:03:39"/>
            <column name="gmt_modified" valueDate="2019-03-12T13:03:51"/>
            <column name="is_deleted" valueNumeric="1"/>
        </insert>
        <insert tableName="t_user_app">
            <column name="id" valueNumeric="42"/>
            <column name="mail_nick_name" value="test"/>
            <column name="app_id" value="loop_test"/>
            <column name="gmt_create" valueDate="2019-03-12T13:52:27"/>
            <column name="gmt_modified" valueDate="2019-03-12T14:04:15"/>
            <column name="is_deleted" valueNumeric="1"/>
        </insert>
        <insert tableName="t_user_app">
            <column name="id" valueNumeric="43"/>
            <column name="mail_nick_name" value="admin"/>
            <column name="app_id" value="loop_test"/>
            <column name="gmt_create" valueDate="2019-03-12T17:37:18"/>
            <column name="gmt_modified" valueDate="2019-03-12T17:37:21"/>
            <column name="is_deleted" valueNumeric="1"/>
        </insert>
        <insert tableName="t_user_app">
            <column name="id" valueNumeric="44"/>
            <column name="mail_nick_name" value="admin"/>
            <column name="app_id" value="loop_test"/>
            <column name="gmt_create" valueDate="2019-03-12T17:37:23"/>
            <column name="gmt_modified" valueDate="2019-03-12T17:37:24"/>
            <column name="is_deleted" valueNumeric="1"/>
        </insert>
        <insert tableName="t_user_app">
            <column name="id" valueNumeric="45"/>
            <column name="mail_nick_name" value="admin"/>
            <column name="app_id" value="loop_test"/>
            <column name="gmt_create" valueDate="2019-03-14T22:13:35"/>
            <column name="gmt_modified" valueDate="2019-03-14T22:13:41"/>
            <column name="is_deleted" valueNumeric="1"/>
        </insert>
        <insert tableName="t_user_app">
            <column name="id" valueNumeric="46"/>
            <column name="mail_nick_name" value="test"/>
            <column name="app_id" value="halo-moss"/>
            <column name="gmt_create" valueDate="2019-03-18T17:17:17"/>
            <column name="gmt_modified" valueDate="2019-03-18T17:17:19"/>
            <column name="is_deleted" valueNumeric="1"/>
        </insert>
        <insert tableName="t_user_app">
            <column name="id" valueNumeric="47"/>
            <column name="mail_nick_name" value="xujin"/>
            <column name="app_id" value="halo-moss"/>
            <column name="gmt_create" valueDate="2019-04-10T19:47:12"/>
            <column name="gmt_modified" valueDate="2019-04-10T19:47:12"/>
            <column name="is_deleted" valueNumeric="0"/>
        </insert>
    </changeSet>
    <changeSet author="liyunlong (generated)" id="1556963101018-19">
        <insert tableName="t_user_roles">
            <column name="id" valueNumeric="11"/>
            <column name="username" value="admin"/>
            <column name="role" value="ADMIN"/>
            <column name="gmt_create" valueDate="2019-03-07T10:24:51"/>
            <column name="gmt_modified" valueDate="2019-03-08T06:27:54"/>
            <column name="is_deleted" valueNumeric="0"/>
        </insert>
        <insert tableName="t_user_roles">
            <column name="id" valueNumeric="12"/>
            <column name="username" value="xujin"/>
            <column name="role" value="ADMIN"/>
            <column name="gmt_create" valueDate="2019-03-08T19:15:41"/>
            <column name="gmt_modified" valueDate="2019-03-09T09:16:52"/>
            <column name="is_deleted" valueNumeric="0"/>
        </insert>
        <insert tableName="t_user_roles">
            <column name="id" valueNumeric="13"/>
            <column name="username" value="test"/>
            <column name="role" value="USER"/>
            <column name="gmt_create" valueDate="1970-01-02T14:00:00"/>
            <column name="gmt_modified" valueDate="2019-03-13T01:52:40"/>
            <column name="is_deleted" valueNumeric="0"/>
        </insert>
    </changeSet>
    <changeSet author="liyunlong (generated)" id="1556963101018-20">
        <addUniqueConstraint columnNames="username, role" constraintName="ix_auth_username" tableName="t_user_roles"/>
    </changeSet>

    <!-- Tag标签分割，用于rollback到此-->
    <changeSet author="liyunlong" id="tag_version_0_1_0">
        <tagDatabase tag="version_0.1.0"/>
    </changeSet>

</databaseChangeLog>
